AUTHORS
CHANGELOG.txt
DESCRIPTION
LICENSE
MANIFEST.in
README.rst
setup.py
django_octocat.egg-info/PKG-INFO
django_octocat.egg-info/SOURCES.txt
django_octocat.egg-info/dependency_links.txt
django_octocat.egg-info/requires.txt
django_octocat.egg-info/top_level.txt
github/__init__.py
github/admin.py
github/backends.py
github/exceptions.py
github/factories.py
github/middlewares.py
github/models.py
github/tasks.py
github/urls.py
github/utils.py
github/views.py
github/migrations/0001_initial.py
github/migrations/0002_auto__chg_field_repository_mirror_url.py
github/migrations/0003_auto__chg_field_repository_homepage.py
github/migrations/0004_auto__add_key.py
github/migrations/__init__.py
github/tests/__init__.py
github/tests/settings.py
github/tests/test_authenticate.py
github/tests/urls.py
github/tests/account/__init__.py
github/tests/account/models.py
github/tests/templates/index.html