Metadata-Version: 1.0
Name: django-octocat
Version: 0.2.1
Summary: A Django app for handling github users and repos.
